pbtestconnect/transform/IExecuteScripts.py
pbtestconnect/transform/Registrations.py
pbtestconnect/transform/__init__.py
pbtestconnect/transform/__main__.py
pbtestconnect-0.0.6.dist-info/METADATA
pbtestconnect-0.0.6.dist-info/WHEEL
pbtestconnect-0.0.6.dist-info/entry_points.txt
pbtestconnect-0.0.6.dist-info/top_level.txt
pbtestconnect-0.0.6.dist-info/RECORD
